kumar/__init__.py
kumar/config.py
kumar/dataset.py
kumar/model.py
kumar/train.py
kumar/diffusion/__init__.py
kumar/diffusion/attention.py
kumar/diffusion/clip.py
kumar/diffusion/ddpm.py
kumar/diffusion/decoder.py
kumar/diffusion/diffusion.py
kumar/diffusion/encoder.py
kumar/diffusion/model_converter.py
kumar/diffusion/model_loader.py
kumar/diffusion/pipeline.py
kumar-5.4.0.dist-info/LICENSE
kumar-5.4.0.dist-info/METADATA
kumar-5.4.0.dist-info/WHEEL
kumar-5.4.0.dist-info/top_level.txt
kumar-5.4.0.dist-info/RECORD
