Metadata-Version: 2.1
Name: kumar
Version: 5.4.0
Summary: `kumar` is a Python package that provides two high-level features.
Author: manishkumar60708090@gmail.com
Author-email: <manishkumar60708090@gmail.com>
Keywords: python,transformer,chat-GPT Transformer
Classifier: Development Status :: 1 - Planning
Classifier: Intended Audience :: Developers
Classifier: Programming Language :: Python :: 3
Classifier: Operating System :: Unix
Classifier: Operating System :: MacOS :: MacOS X
Classifier: Operating System :: Microsoft :: Windows
License-File: LICENSE
Requires-Dist: torch
Requires-Dist: tqdm
Requires-Dist: datasets
Requires-Dist: tokenizers
Requires-Dist: tensorboard
Requires-Dist: pathlib
Requires-Dist: pillow
Requires-Dist: numpy
Requires-Dist: transformers
Requires-Dist: pytorch-lightning
